portal_facil_sdk/__init__.py
portal_facil_sdk/controllers/atendimento_controller.py
portal_facil_sdk/entities/beneficiario.py
portal_facil_sdk/entities/guia_beneficiario.py
portal_facil_sdk/entities/procedimento.py
portal_facil_sdk/entities/ticket.py
portal_facil_sdk/factories/beneficiario_factory.py
portal_facil_sdk/factories/guia_beneficiario_factory.py
portal_facil_sdk/factories/procedimento_factory.py
portal_facil_sdk/factories/ticket_factory.py
portal_facil_sdk/providers/crm_provider.py
portal_facil_sdk/services/cache_service.py
portal_facil_sdk/tests/__init__.py
portal_facil_sdk/tests/constants.py
portal_facil_sdk/tests/test_atendimento_controller.py
portal_facil_sdk/tests/test_beneficiario.py
portal_facil_sdk/tests/test_crm_provider.py
portal_facil_sdk/tests/test_guia_beneficiario.py
portal_facil_sdk/tests/test_procedimentos.py
portal_facil_sdk/tests/test_ticket.py
portal_facil_sdk-0.3.1.dist-info/licenses/LICENSE
portal_facil_sdk-0.3.1.dist-info/METADATA
portal_facil_sdk-0.3.1.dist-info/WHEEL
portal_facil_sdk-0.3.1.dist-info/top_level.txt
portal_facil_sdk-0.3.1.dist-info/RECORD
