Metadata-Version: 2.4
Name: portal-facil-sdk
Version: 0.3.1
Summary: Portal Facil CRM API SDK
Author: Tatianno Alves
Author-email: tferreiraalves@gmail.com
License: MIT License
Keywords: portal facil CRM SDK
License-File: LICENSE
Requires-Dist: requests==2.32.5
Dynamic: author
Dynamic: author-email
Dynamic: description
Dynamic: description-content-type
Dynamic: keywords
Dynamic: license
Dynamic: license-file
Dynamic: requires-dist
Dynamic: summary
